chain_processor/__init__.py
chain_processor/base.py
chain_processor/utils.py
chain_processor-0.1.5.dist-info/LICENSE
chain_processor-0.1.5.dist-info/METADATA
chain_processor-0.1.5.dist-info/WHEEL
chain_processor-0.1.5.dist-info/RECORD
