Metadata-Version: 2.1
Name: chain_processor
Version: 0.1.5
Summary: A library for creating and managing chains of function nodes.
Home-page: https://github.com/lf-data/chain_processor
License: Apache-2.0
Author: Francesco Lorè
Author-email: flore9819@gmail.com
Requires-Python: >=3.8
Classifier: License :: OSI Approved :: Apache Software License
Classifier: Operating System :: OS Independent
Classifier: Programming Language :: Python :: 3
Classifier: Programming Language :: Python :: 3.8
Classifier: Programming Language :: Python :: 3.9
Classifier: Programming Language :: Python :: 3.10
Classifier: Programming Language :: Python :: 3.11
Classifier: Programming Language :: Python :: 3.12
Requires-Dist: colorama (>=0.4.6,<0.5.0)
Requires-Dist: graphviz (>=0.20.3,<0.21.0)
Project-URL: Bug Tracker, https://github.com/lf-data/chain_processor/issues
Project-URL: Repository, https://github.com/lf-data/chain_processor
